akellogpt/__init__.py
akellogpt/settings.py
akellogpt/common/__init__.py
akellogpt/common/api.py
akellogpt/screening/__init__.py
akellogpt/screening/mental_health.py
akellogpt/screening/yaml/__init__.py
akellogpt/screening/yaml/gad7.yaml
akellogpt/screening/yaml/phq9.yaml
akellogpt/screening/yaml/sbq-r.yaml
akellogpt/test/__init__.py
akellogpt/test/test_gad7.py
akellogpt/test/test_phq9.py
common/__init__.py
common/api.py
screening/__init__.py
screening/mental_health.py
test/__init__.py
test/test_gad7.py
test/test_phq9.py
akellogpt-0.0.4.dist-info/LICENSE
akellogpt-0.0.4.dist-info/METADATA
akellogpt-0.0.4.dist-info/WHEEL
akellogpt-0.0.4.dist-info/top_level.txt
akellogpt-0.0.4.dist-info/RECORD
